LICENSE
README.md
setup.cfg
setup.py
trendpy/__init__.py
trendpy/factory.py
trendpy/globals.py
trendpy/mcmc.py
trendpy/samplers.py
trendpy/version.py
trendpy.egg-info/PKG-INFO
trendpy.egg-info/SOURCES.txt
trendpy.egg-info/dependency_links.txt
trendpy.egg-info/not-zip-safe
trendpy.egg-info/requires.txt
trendpy.egg-info/top_level.txt