Metadata-Version: 1.1
Name: trendpy
Version: 1.0.0
Summary: Trend Filtering Python Micro Framework
Home-page: https://github.com/RonsenbergVI/trendpy
Author: Rene-Jean Corneille
Author-email: rene_jean.corneille@edu.escpeurope.eu
License: MIT
Keywords: trend,finance,pandas,seaborn,filter,trading,stocks,equities,forex
Platform: any
Classifier: Development Status :: 2 - Pre-Alpha
Classifier: Environment :: Web Environment
Classifier: Intended Audience :: Financial and Insurance Industry
Classifier: License :: OSI Approved :: MIT License
Classifier: Operating System :: OS Independent
Classifier: Programming Language :: Python
Classifier: Programming Language :: Python :: 3
Classifier: Programming Language :: Python :: 3.3
Classifier: Programming Language :: Python :: 3.4
Classifier: Programming Language :: Python :: 3.5
Classifier: Programming Language :: Python :: 3.6
Classifier: Topic :: Scientific/Engineering :: Mathematics
Classifier: Topic :: Software Development :: Libraries :: Python Modules
